{
  "project_info": {
    "project_number": "191198007413",
    "firebase_url": "https://sandbox-lp.firebaseio.com",
    "project_id": "sandbox-lp",
    "storage_bucket": "sandbox-lp.appspot.com"
  },
  "client": [
    {
      "client_info": {
        "mobilesdk_app_id": "1:191198007413:android:1ab65b4ee6ff448d",
        "android_client_info": {
          "package_name": "com.grahm.livepost"
        }
      },
      "oauth_client": [
        {
          "client_id": "191198007413-3e2e57pkr9krigqaut8vgrf8qdpnuobi.apps.googleusercontent.com",
          "client_type": 3
        }
      ],
      "api_key": [
        {
          "current_key": "AIzaSyAX8ZyIRt_cHdPmusz7W8O1P_2TaG9JlTU"
        }
      ],
      "services": {
        "analytics_service": {
          "status": 1
        },
        "appinvite_service": {
          "status": 1,
          "other_platform_oauth_client": []
        },
        "ads_service": {
          "status": 2
        }
      }
    }
  ],
  "configuration_version": "1"
}